wipeout/__init__.py
wipeout/debugging.py
wipeout/fake_traceback.py
wipeout/load.py
wipeout/run.py
wipeout-0.0.1.dist-info/WHEEL
wipeout-0.0.1.dist-info/METADATA
wipeout-0.0.1.dist-info/RECORD
