Metadata-Version: 2.1
Name: wipeout
Version: 0.0.1
Summary: Tooling for debugging later
Requires-Python: >= 3.10
Requires-Dist: rich>=13.7.1
Requires-Dist: tblib>=3.0.0
Requires-Dist: traceback-with-variables>=2.0.4
Requires-Dist: dill>=0.3.8
Requires-Dist: typer>=0.12.3
Requires-Dist: fsspec>=2024.6.1
